haystack_integrations/components/retrievers/py.typed
haystack_integrations/components/retrievers/pinecone/__init__.py
haystack_integrations/components/retrievers/pinecone/embedding_retriever.py
haystack_integrations/document_stores/py.typed
haystack_integrations/document_stores/pinecone/__init__.py
haystack_integrations/document_stores/pinecone/document_store.py
haystack_integrations/document_stores/pinecone/filters.py
pinecone_haystack-6.0.0.dist-info/METADATA
pinecone_haystack-6.0.0.dist-info/WHEEL
pinecone_haystack-6.0.0.dist-info/RECORD
