Metadata-Version: 2.4
Name: pinecone_haystack
Version: 6.0.0
Project-URL: Documentation, https://github.com/deepset-ai/haystack-core-integrations/tree/main/integrations/pinecone#readme
Project-URL: Issues, https://github.com/deepset-ai/haystack-core-integrations/issues
Project-URL: Source, https://github.com/deepset-ai/haystack-core-integrations/tree/main/integrations/pinecone
Author-email: deepset GmbH <info@deepset.ai>
License-Expression: Apache-2.0
Classifier: Development Status :: 4 - Beta
Classifier: License :: OSI Approved :: Apache Software License
Classifier: Programming Language :: Python
Classifier: Programming Language :: Python :: 3.10
Classifier: Programming Language :: Python :: 3.11
Classifier: Programming Language :: Python :: 3.12
Classifier: Programming Language :: Python :: 3.13
Classifier: Programming Language :: Python :: Implementation :: CPython
Classifier: Programming Language :: Python :: Implementation :: PyPy
Requires-Python: >=3.10
Requires-Dist: haystack-ai>=2.22.0
Requires-Dist: pinecone[asyncio]>=7.0.0
